symdet/__init__.py
symdet/analysis/__init__.py
symdet/analysis/model_visualization.py
symdet/data/__init__.py
symdet/data/data_generator.py
symdet/data/double_well_potential.py
symdet/data/so2_data.py
symdet/data/so3_data.py
symdet/generator_extraction/__init__.py
symdet/generator_extraction/generators.py
symdet/ml_models/__init__.py
symdet/ml_models/dense_model.py
symdet/symmetry_group_extraction/__init__.py
symdet/symmetry_group_extraction/group_detection.py
symdet/utils/__init__.py
symdet/utils/data_clustering.py
SymDet-0.0.1.dist-info/LICENSE
SymDet-0.0.1.dist-info/METADATA
SymDet-0.0.1.dist-info/WHEEL
SymDet-0.0.1.dist-info/top_level.txt
SymDet-0.0.1.dist-info/RECORD
