Metadata-Version: 2.1
Name: SymDet
Version: 0.0.1
Summary: Symmetry detection and Lie generator extraction.
Home-page: https://github.com/SamTov/SymDet
Author: Samuel Tovey
Author-email: tovey.samuel@gmail.com
License: UNKNOWN
Platform: UNKNOWN
Classifier: Programming Language :: Python :: 3
Classifier: License :: OSI Approved :: GNU General Public License v3 (GPLv3)
Classifier: Operating System :: OS Independent
Requires-Python: >=3.6
License-File: LICENSE
Requires-Dist: numpy
Requires-Dist: nbsphinx
Requires-Dist: tensorflow
Requires-Dist: sklearn
Requires-Dist: sphinx-rtd-theme
Requires-Dist: sphinx-copybutton
Requires-Dist: matplotlib
Requires-Dist: tqdm
Requires-Dist: IPython
Requires-Dist: pandoc
Requires-Dist: numpydoc
Requires-Dist: pre-commit
